_hal_constants
hal
