Metadata-Version: 1.1
Name: robotpy-hal-base
Version: 2019.2.3
Summary: WPILib Hardware Abstration Layer base
Home-page: https://github.com/robotpy/robotpy-wpilib
Author: Peter Johnson, Dustin Spicuzza
Author-email: robotpy@googlegroups.com
License: BSD License
Keywords: frc first robotics hal can
Platform: UNKNOWN
Classifier: Development Status :: 5 - Production/Stable
Classifier: Intended Audience :: Developers
Classifier: Intended Audience :: Education
Classifier: License :: OSI Approved :: BSD License
Classifier: Operating System :: OS Independent
Classifier: Programming Language :: Python :: 3.5
Classifier: Programming Language :: Python :: 3.6
Classifier: Topic :: Scientific/Engineering
